scm_source/__init__.py
scm_source/__main__.py
scm_source/api.py
scm_source/cli.py
scm_source-1.0.11.dist-info/DESCRIPTION.rst
scm_source-1.0.11.dist-info/METADATA
scm_source-1.0.11.dist-info/RECORD
scm_source-1.0.11.dist-info/WHEEL
scm_source-1.0.11.dist-info/entry_points.txt
scm_source-1.0.11.dist-info/metadata.json
scm_source-1.0.11.dist-info/top_level.txt
