Metadata-Version: 2.0
Name: scm-source
Version: 1.0.11
Summary: CLI to generate scm-source.json
Home-page: https://github.com/zalando-stups/python-scm-source
Author: Henning Jacobs
Author-email: henning.jacobs@zalando.de
License: Apache License Version 2.0
Keywords: stups scm source git revision
Platform: UNKNOWN
Classifier: Programming Language :: Python
Classifier: Programming Language :: Python :: 3.4
Classifier: Development Status :: 4 - Beta
Classifier: Intended Audience :: Developers
Classifier: Operating System :: OS Independent
Requires-Dist: PyYAML
Requires-Dist: clickclick
